rabbitmqpubsub/__init__.py
rabbitmqpubsub/rabbit_pubsub/__init__.py
rabbitmqpubsub/rabbit_pubsub/arpcclient.py
rabbitmqpubsub/rabbit_pubsub/publisher.py
rabbitmqpubsub/rabbit_pubsub/rpcclient.py
rabbitmqpubsub/rabbit_pubsub/subscriber.py
rabbitmqpubsub/tests/__init__.py
rabbitmqpubsub/tests/test_subscriber.py
rabbitmqpubsub-1.4.0.dist-info/licenses/LICENSE
rabbitmqpubsub-1.4.0.dist-info/WHEEL
rabbitmqpubsub-1.4.0.dist-info/METADATA
rabbitmqpubsub-1.4.0.dist-info/RECORD
