Metadata-Version: 2.4
Name: RabbitMQPubSub
Version: 1.4.0
Summary: RabbitMQ helpers for pubsub.
Author-email: Nebojsa Mrkic <mrkic.nebojsa@gmail.com>
Classifier: License :: OSI Approved :: Apache Software License
License-File: LICENSE
Requires-Dist: pika>=1.3.0
Requires-Dist: dateutils
Requires-Dist: aiormq
Requires-Dist: orjson
Requires-Dist: flit>=3.11.0
Requires-Dist: pytest ; extra == "tests"
Requires-Dist: coverage ; extra == "tests"
Requires-Dist: mock ; extra == "tests"
Requires-Dist: requests ; extra == "tests"
Requires-Dist: pytest-runner ; extra == "tests"
Requires-Dist: pre-commit ; extra == "tests"
Requires-Dist: pytest-mock ; extra == "tests"
Project-URL: Home, https://github.com/nmrkic/RabbitMQPubSub
Provides-Extra: tests
